loadingbar/__init__.py
loadingbar/aloadingbar.py
loadingbar/background.py
loadingbar/bars.py
loadingbar/indicator.py
loadingbar/infos.py
loadingbar-1.0.0.dist-info/METADATA
loadingbar-1.0.0.dist-info/RECORD
loadingbar-1.0.0.dist-info/WHEEL
loadingbar-1.0.0.dist-info/top_level.txt
