Metadata-Version: 2.1
Name: loadingbar
Version: 1.0.0
Summary: Library to display a loading bar in a terminal.
Home-page: https://github.com/theeko74/loading
Author: Sylvain Carlioz
Author-email: sylvain.carlioz@gmail.com
License: MIT
Keywords: loading,loading bar,terminal
Platform: UNKNOWN
Classifier: Development Status :: 5 - Production/Stable
Classifier: License :: OSI Approved :: MIT License
Classifier: Operating System :: OS Independent
Classifier: Programming Language :: Python :: 3
Classifier: Programming Language :: Python :: 2
